LICENSE.txt
MANIFEST.in
README.md
setup.py
src/eirx/__init__.py
src/eirx/api.py
src/eirx/main.py
src/eirx/parse.py
src/eirx.egg-info/PKG-INFO
src/eirx.egg-info/SOURCES.txt
src/eirx.egg-info/dependency_links.txt
src/eirx.egg-info/entry_points.txt
src/eirx.egg-info/not-zip-safe
src/eirx.egg-info/requires.txt
src/eirx.egg-info/top_level.txt