Metadata-Version: 1.0
Name: eirx
Version: 0.30
Summary: Simple image manipulate based on Pillow.
Home-page: https://github.com/neuront/eirx
Author: Neuron Teckid
Author-email: lene13@gmail.com
License: MIT
Keywords: image manipulate resize crop
Platform: UNKNOWN
